vsutillib/files/__init__.py
vsutillib/files/fileutil.py
vsutillib/files/classes/DisplayPath.py
vsutillib/files/classes/__init__.py
vsutillib/files/classes/configurationsettings.py
vsutillib_files-1.6.3.dist-info/AUTHORS
vsutillib_files-1.6.3.dist-info/LICENSE.txt
vsutillib_files-1.6.3.dist-info/METADATA
vsutillib_files-1.6.3.dist-info/WHEEL
vsutillib_files-1.6.3.dist-info/top_level.txt
vsutillib_files-1.6.3.dist-info/RECORD
