Metadata-Version: 2.1
Name: vsutillib-files
Version: 1.6.3
Summary: vsutillib.files sub package part of vsutillib
Home-page: https://pypi.org/project/vsutillib-files/
Author: Efrain Vergara
Author-email: akai10tsuki@gmail.com
License: MIT
Platform: UNKNOWN
Requires-Python: >=3.8.1, <3.9
